ament_cmake_export_targets/_dummy.cpython-312-x86_64-linux-gnu.so
ros_ament_cmake_export_targets-2.7.3.data/data/share/ament_cmake_export_targets/local_setup.bash
ros_ament_cmake_export_targets-2.7.3.data/data/share/ament_cmake_export_targets/local_setup.dsv
ros_ament_cmake_export_targets-2.7.3.data/data/share/ament_cmake_export_targets/local_setup.sh
ros_ament_cmake_export_targets-2.7.3.data/data/share/ament_cmake_export_targets/local_setup.zsh
ros_ament_cmake_export_targets-2.7.3.data/data/share/ament_cmake_export_targets/package.dsv
ros_ament_cmake_export_targets-2.7.3.data/data/share/ament_cmake_export_targets/package.xml
ros_ament_cmake_export_targets-2.7.3.data/data/share/ament_cmake_export_targets/cmake/ament_cmake_export_targets-extras.cmake
ros_ament_cmake_export_targets-2.7.3.data/data/share/ament_cmake_export_targets/cmake/ament_cmake_export_targets-extras.cmake.in
ros_ament_cmake_export_targets-2.7.3.data/data/share/ament_cmake_export_targets/cmake/ament_cmake_export_targetsConfig-version.cmake
ros_ament_cmake_export_targets-2.7.3.data/data/share/ament_cmake_export_targets/cmake/ament_cmake_export_targetsConfig.cmake
ros_ament_cmake_export_targets-2.7.3.data/data/share/ament_cmake_export_targets/cmake/ament_cmake_export_targets_package_hook.cmake
ros_ament_cmake_export_targets-2.7.3.data/data/share/ament_cmake_export_targets/cmake/ament_export_targets.cmake
ros_ament_cmake_export_targets-2.7.3.data/data/share/ament_cmake_export_targets/environment/ament_prefix_path.dsv
ros_ament_cmake_export_targets-2.7.3.data/data/share/ament_cmake_export_targets/environment/ament_prefix_path.sh
ros_ament_cmake_export_targets-2.7.3.data/data/share/ament_cmake_export_targets/environment/path.dsv
ros_ament_cmake_export_targets-2.7.3.data/data/share/ament_cmake_export_targets/environment/path.sh
ros_ament_cmake_export_targets-2.7.3.data/data/share/ament_index/resource_index/package_run_dependencies/ament_cmake_export_targets
ros_ament_cmake_export_targets-2.7.3.dist-info/METADATA
ros_ament_cmake_export_targets-2.7.3.dist-info/WHEEL
ros_ament_cmake_export_targets-2.7.3.dist-info/top_level.txt
ros_ament_cmake_export_targets-2.7.3.dist-info/RECORD
